siconv/__init__.py
siconv/test.py
siconv/to_singlish.py
siconv/to_sinhala.py
siconv-0.1.2.9.dist-info/LICENSE
siconv-0.1.2.9.dist-info/METADATA
siconv-0.1.2.9.dist-info/WHEEL
siconv-0.1.2.9.dist-info/top_level.txt
siconv-0.1.2.9.dist-info/RECORD
